crochetcalculator/__init__.py
crochetcalculator/config.txt
crochetcalculator/gauge.py
crochetcalculator-0.0.4.dist-info/LICENSE
crochetcalculator-0.0.4.dist-info/WHEEL
crochetcalculator-0.0.4.dist-info/METADATA
crochetcalculator-0.0.4.dist-info/RECORD
