Metadata-Version: 2.1
Name: crochetcalculator
Version: 0.0.4
Summary: Calculate crochet patterns
License: MIT
Author: alicew
Requires-Python: >=3.9,<4.0
Classifier: License :: OSI Approved :: MIT License
Classifier: Programming Language :: Python :: 3
Classifier: Programming Language :: Python :: 3.10
Classifier: Programming Language :: Python :: 3.9
